{
  "size": "300x600",
  "stageSize": {
    "width": 300,
    "height": 600
  },
  "layers": [
    {
      "id": "background",
      "name": "Background",
      "type": "color",
      "x": 0,
      "y": 0,
      "width": 300,
      "height": 600,
      "fill": "#f0f0f0",
      "visible": true,
      "opacity": 1,
      "blendMode": "normal",
      "locked": false
    },
    {
      "id": "text",
      "name": "Text",
      "type": "text",
      "content": "Big\nSavings\nToday",
      "x": 30,
      "y": 250,
      "width": 240,
      "height": 150,
      "fill": "#000000",
      "visible": true,
      "opacity": 1,
      "blendMode": "normal",
      "font": {
        "family": "Arial",
        "size": 42,
        "weight": 700,
        "style": "normal",
        "letterSpacing": 0,
        "lineHeight": 1.2
      },
      "alignment": "center",
      "locked": false
    }
  ],
  "animations": [
    {
      "layerId": "text",
      "keyframes": [
        { "frame": 0, "opacity": 0, "y": 200, "easing": "linear" },
        { "frame": 24, "opacity": 1, "y": 250, "easing": "power2.out" }
      ],
      "loop": true
    }
  ],
  "fps": 60,
  "duration": 5
} 